qiskit_aer/__init__.py
qiskit_aer/version.py
qiskit_aer/VERSION.txt
qiskit_aer/aerprovider.py
qiskit_aer/aererror.py
qiskit_aer/jobs/utils.py
qiskit_aer/jobs/aerjob.py
qiskit_aer/jobs/__init__.py
qiskit_aer/utils/__init__.py
qiskit_aer/utils/noise_transformation.py
qiskit_aer/utils/noise_model_inserter.py
qiskit_aer/quantum_info/__init__.py
qiskit_aer/quantum_info/states/aer_densitymatrix.py
qiskit_aer/quantum_info/states/__init__.py
qiskit_aer/quantum_info/states/aer_state.py
qiskit_aer/quantum_info/states/aer_statevector.py
qiskit_aer/primitives/sampler_v2.py
qiskit_aer/primitives/sampler.py
qiskit_aer/primitives/estimator_v2.py
qiskit_aer/primitives/__init__.py
qiskit_aer/primitives/estimator.py
qiskit_aer/backends/compatibility.py
qiskit_aer/backends/backendproperties.py
qiskit_aer/backends/aer_compiler.py
qiskit_aer/backends/controller_wrappers.cpython-312-x86_64-linux-gnu.so
qiskit_aer/backends/backend_utils.py
qiskit_aer/backends/unitary_simulator.py
qiskit_aer/backends/__init__.py
qiskit_aer/backends/backendconfiguration.py
qiskit_aer/backends/statevector_simulator.py
qiskit_aer/backends/aerbackend.py
qiskit_aer/backends/name_mapping.py
qiskit_aer/backends/qasm_simulator.py
qiskit_aer/backends/aer_simulator.py
qiskit_aer/library/default_qubits.py
qiskit_aer/library/__init__.py
qiskit_aer/library/instructions_table.csv
qiskit_aer/library/set_instructions/set_stabilizer.py
qiskit_aer/library/set_instructions/set_superop.py
qiskit_aer/library/set_instructions/set_statevector.py
qiskit_aer/library/set_instructions/__init__.py
qiskit_aer/library/set_instructions/set_matrix_product_state.py
qiskit_aer/library/set_instructions/set_unitary.py
qiskit_aer/library/set_instructions/set_density_matrix.py
qiskit_aer/library/control_flow_instructions/store.py
qiskit_aer/library/control_flow_instructions/mark.py
qiskit_aer/library/control_flow_instructions/__init__.py
qiskit_aer/library/control_flow_instructions/jump.py
qiskit_aer_gpu_cu11-0.17.2.dist-info/METADATA
qiskit_aer_gpu_cu11-0.17.2.dist-info/top_level.txt
qiskit_aer_gpu_cu11-0.17.2.dist-info/WHEEL
qiskit_aer_gpu_cu11-0.17.2.dist-info/RECORD
qiskit_aer_gpu_cu11-0.17.2.dist-info/licenses/LICENSE.txt
